a_api_server/__about__.py
a_api_server/__init__.py
a_api_server/api_server.py
A_Api_Server-1.2.2.dist-info/METADATA
A_Api_Server-1.2.2.dist-info/WHEEL
A_Api_Server-1.2.2.dist-info/entry_points.txt
A_Api_Server-1.2.2.dist-info/top_level.txt
A_Api_Server-1.2.2.dist-info/RECORD
