Metadata-Version: 2.1
Name: A-Api-Server
Version: 1.2.2
Summary: 自建一个Resful风格的接口自助服务，方便API自动化测试工具的开发与调试！
Home-page: https://github.com/zhuifengshen/a-api-server
Author: devin
Author-email: 1324556701@qq.com
License: MIT
Keywords: ApiServer,Api,MockServer,Api Test,接口测试,接口自动化测试
Platform: UNKNOWN
Classifier: Development Status :: 5 - Production/Stable
Classifier: Programming Language :: Python :: 2.7
Classifier: Programming Language :: Python :: 3.4
Classifier: Programming Language :: Python :: 3.5
Classifier: Programming Language :: Python :: 3.6
Classifier: Programming Language :: Python :: 3.7
Classifier: Programming Language :: Python :: 3.8
Classifier: License :: OSI Approved :: MIT License
Classifier: Operating System :: OS Independent
Requires-Python: >=2.7, <4
Requires-Dist: flask
